langchain_dashscope/__init__.py
langchain_dashscope/aigc_generation.py
langchain_dashscope/embeddings.py
langchain_dashscope-0.1.8.dist-info/LICENSE
langchain_dashscope-0.1.8.dist-info/METADATA
langchain_dashscope-0.1.8.dist-info/WHEEL
langchain_dashscope-0.1.8.dist-info/RECORD
