Metadata-Version: 2.1
Name: langchain_dashscope
Version: 0.1.8
Summary: 将阿里云灵积模型（通义千问等）集成到LangChain
License: MIT
Author: arcstep
Author-email: 43801@qq.com
Requires-Python: >=3.9,<4.0
Classifier: License :: OSI Approved :: MIT License
Classifier: Programming Language :: Python :: 3
Classifier: Programming Language :: Python :: 3.9
Classifier: Programming Language :: Python :: 3.10
Classifier: Programming Language :: Python :: 3.11
Classifier: Programming Language :: Python :: 3.12
Requires-Dist: dashscope (>=1.14.1,<2.0.0)
Requires-Dist: tiktoken (>=0.7.0,<0.8.0)
